mate/__init__.py
mate/mate.py
mate/matelightning.py
mate/array/__init__.py
mate/array/module.py
mate/dataset/__init__.py
mate/dataset/mlpair.py
mate/preprocess/__init__.py
mate/preprocess/discretizer.py
mate/preprocess/discretizerfactory.py
mate/preprocess/interpdiscretizer.py
mate/preprocess/shiftdiscretizer.py
mate/preprocess/tagdiscretizer.py
mate/transferentropy/__init__.py
mate/transferentropy/infodynamics.jar
mate/transferentropy/telightning.py
mate/transferentropy/tenet.py
mate/transferentropy/transferentropy.py
mate/utils/__init__.py
mate/utils/utils.py
mate_cxinsys-2.0.6.dist-info/LICENSE
mate_cxinsys-2.0.6.dist-info/METADATA
mate_cxinsys-2.0.6.dist-info/WHEEL
mate_cxinsys-2.0.6.dist-info/top_level.txt
mate_cxinsys-2.0.6.dist-info/RECORD
