Metadata-Version: 2.1
Name: mate-cxinsys
Version: 2.0.6
Summary: MATE
Home-page: https://github.com/cxinsys/mate
Author: Complex Intelligent Systems Laboratory (CISLAB)
Author-email: daewon4you@gmail.com
License: BSD-3-Clause
License-File: LICENSE
Requires-Dist: numpy
Requires-Dist: scipy
Requires-Dist: lightning
Requires-Dist: JPype1
